cursor_memory_mcp/__init__.py
cursor_memory_mcp/server.py
cursor_memory_mcp-0.1.1.dist-info/METADATA
cursor_memory_mcp-0.1.1.dist-info/WHEEL
cursor_memory_mcp-0.1.1.dist-info/entry_points.txt
cursor_memory_mcp-0.1.1.dist-info/RECORD
